iocparser/README.md
iocparser/__init__.py
iocparser/__main__.py
iocparser/core.py
iocparser/main.py
iocparser/modules/__init__.py
iocparser/modules/config.py
iocparser/modules/exceptions.py
iocparser/modules/extractor.py
iocparser/modules/extractor_aggregate.py
iocparser/modules/extractor_artifacts.py
iocparser/modules/extractor_base.py
iocparser/modules/extractor_hashes.py
iocparser/modules/extractor_network.py
iocparser/modules/extractor_patterns.py
iocparser/modules/file_parser.py
iocparser/modules/logger.py
iocparser/modules/output_formatter.py
iocparser/modules/persistence.py
iocparser/modules/streaming.py
iocparser/modules/utils.py
iocparser/modules/warninglists.py
iocparser/modules/warninglists_diagnostics.py
iocparser/modules/data/legitimate_domains.json
iocparser/modules/data/misp_warninglists_cache.json
iocparser/modules/data/misp_warninglists_metadata.json
iocparser_tool-5.0.1.dist-info/licenses/LICENSE
iocparser_tool-5.0.1.dist-info/METADATA
iocparser_tool-5.0.1.dist-info/WHEEL
iocparser_tool-5.0.1.dist-info/entry_points.txt
iocparser_tool-5.0.1.dist-info/top_level.txt
iocparser_tool-5.0.1.dist-info/RECORD
