Metadata-Version: 2.4
Name: iocparser-tool
Version: 5.0.1
Summary: A tool for extracting Indicators of Compromise from security reports
Home-page: https://github.com/seifreed/iocparser
Author: Marc Rivero
Author-email: 
Maintainer: Marc Rivero
License: MIT
Project-URL: Homepage, https://github.com/seifreed/iocparser
Project-URL: Documentation, https://github.com/seifreed/iocparser#readme
Project-URL: Repository, https://github.com/seifreed/iocparser
Project-URL: Bug Tracker, https://github.com/seifreed/iocparser/issues
Keywords: security,ioc,malware,threat-intelligence,pdf,html,parser
Classifier: Development Status :: 5 - Production/Stable
Classifier: Intended Audience :: Information Technology
Classifier: Intended Audience :: System Administrators
Classifier: License :: OSI Approved :: MIT License
Classifier: Operating System :: OS Independent
Classifier: Programming Language :: Python :: 3
Classifier: Programming Language :: Python :: 3.10
Classifier: Programming Language :: Python :: 3.11
Classifier: Programming Language :: Python :: 3.12
Classifier: Programming Language :: Python :: 3.13
Classifier: Topic :: Security
Classifier: Topic :: Software Development :: Libraries :: Python Modules
Classifier: Topic :: Text Processing :: Filters
Requires-Python: >=3.10
License-File: LICENSE
Requires-Dist: colorama>=0.4.6
Requires-Dist: python-magic>=0.4.27
Requires-Dist: requests>=2.32.5
Requires-Dist: urllib3>=2.6.3
Requires-Dist: tqdm>=4.67.1
Requires-Dist: pdfplumber>=0.11.9
Requires-Dist: beautifulsoup4>=4.14.3
Requires-Dist: lxml>=6.0.2
Requires-Dist: regex>=2025.11.3
Requires-Dist: pdfminer.six>=20251230
Requires-Dist: stix2>=3.0.1
Requires-Dist: sqlalchemy>=2.0.43
Requires-Dist: pymysql>=1.1.1
Requires-Dist: python-dotenv>=1.0.1
Provides-Extra: dev
Requires-Dist: pytest>=9.0.2; extra == "dev"
Requires-Dist: pytest-cov>=7.0.0; extra == "dev"
Requires-Dist: pytest-benchmark>=5.2.3; extra == "dev"
Requires-Dist: ruff>=0.14.11; extra == "dev"
Requires-Dist: mypy>=1.19.1; extra == "dev"
Requires-Dist: bandit[toml]>=1.9.2; extra == "dev"
Requires-Dist: pylint>=4.0.4; extra == "dev"
Requires-Dist: pre-commit>=4.5.1; extra == "dev"
Requires-Dist: types-requests>=2.32.4.20260107; extra == "dev"
Requires-Dist: types-setuptools>=80.9.0.20250822; extra == "dev"
Requires-Dist: types-colorama>=0.4.15.20250801; extra == "dev"
Requires-Dist: types-tqdm>=4.67.0.20250809; extra == "dev"
Dynamic: home-page
Dynamic: license-file
Dynamic: requires-python
